{
  "persons": [
    {
      "name": "Dan Abramov",
      "number": "12-43-234345",
      "id": 3
    },
    {
      "name": "adasd",
      "number": "sadasdas",
      "id": "b89e"
    },
    {
      "name": "adasdsaasdad",
      "number": "sadasdas",
      "id": "9120"
    },
    {
      "name": "dadsa",
      "number": "dadada",
      "id": "fa09"
    },
    {
      "name": "daddy doo",
      "number": "dadada",
      "id": "b329"
    },
    {
      "name": "asdasd",
      "number": "asdasdad",
      "id": "ba85"
    }
  ]
}